[{"jyakunenseinyusyo": "なし", "hp_address": "http://www.nagao.or.jp/fujigaokasou/", "tel": "092-511-1070", "taisyogoshido": "なし", "taisyomaerenkei": "なし", "eiyomanage": "なし", "municipality": "福岡市南区", "manager_name": "栗林　仁信", "semi_unitcare": "なし", "nitijyokeizoku": "なし", "name_furi": "ちいきみっちゃくがたとくべつようごろうじんほーむ　ふじがおかそう", "zaitakuhukki": "なし", "postcode": "〒811-1355", "keikoikou": "なし", "zaitakunyusyo": "なし", "service_supply_1": "あり", "service_supply_2": "なし", "service_supply_3": "なし", "nightdutyhaichi": "あり", "daily_life_price": "希望により提供した日常生活品費の実費", "nintisyoshinritaio": "なし", "special_meal_price": "嗜好品等利用者個人の要望にかかる各種経費等の実費", "founding_day": "2012/04/01※半角で記入してください（例：2013/04/01）", "private_kinou": "なし", "kouku": "なし", "kangotaisei_2": "あり", "kangotaisei_1": "あり", "unit_privateroom": "", "latitude": "33.539827200000000", "nintisyosenmon_1": "なし", "nintisyosenmon_2": "なし", "syogaisyashien": "なし", "keikoiji": "なし", "fax": "092-511-1078", "carestaffkaizen_3": "なし", "carestaffkaizen_2": "なし", "carestaffkaizen_1": "あり", "small_kyoten": "なし", "company_type": "社会福祉法人（社協以外）", "company": "社会福祉法人　順和", "unit_semi_privateroom": "", "residence_price": "1,770円、一日算定。\r\n負担限度額認定の対象の方は、1日に付き、1段階…820円・2段階…820円・3段階…1,350円の負担", "doctor_haiti": "なし", "service_type": "\n地域密着型介護老人福祉施設入所者生活介護", "caregiving": "なし", "traffic": "《西鉄バス利用の場合》\r\n・天神より\r\n　12-1　13　52　56　57　桧原営業所・柏原営業所行き「桧原三ツ角」下車\r\n・博多駅より\r\n　12-1　13　56　57　桧原営業所・柏原営業所行き「桧原三ツ角」下車\r\n　（下車後、小笹方面に進み「桧原２丁目」の交差点（びっくりドンキーの角）を右折します。こひつじ幼稚園隣。）\r\n・大橋駅より\r\n　700　福大病院行き「桧原桜前」下車\r\n　（下車後、長住方面を背にして、ゆるやかな坂道を下ります。左手にセブンイレブンがあり、その向かい側。）", "medical_meal": "あり", "existingroom": "", "hairdressing_price": "希望により提供した理美容に要した費用の実費", "name": "地域密着型特別養護老人ホーム　藤ヶ丘荘", "multibedroom": "", "taisyojisoudan": "なし", "meal_price": "1,380円、一日算定。\r\n負担限度額認定の対象の方は、1日に付き、1段階…300円・2段階…390円・3段階…650円の負担", "taisyomaesoudan": "なし", "seishinkairyo": "なし", "longitude": "130.393854000000030", "koukutaisei": "あり", "address_1": "福岡市南区桧原1丁目18-11", "userchargecut": "なし", "office_no": "4091100125", "address_2": "", "special_room_price": "なし"},
{"jyakunenseinyusyo": "なし", "hp_address": "http://www.m-h.jp", "tel": "092-892-3315", "taisyogoshido": "なし", "taisyomaerenkei": "なし", "eiyomanage": "あり", "municipality": "福岡市西区", "manager_name": "加藤　めぐみ", "semi_unitcare": "なし", "nitijyokeizoku": "あり", "name_furi": "とくべつようごろうじんほーむ　まいねすはうすふくしげ", "zaitakuhukki": "なし", "postcode": "〒819-0022", "keikoikou": "なし", "zaitakunyusyo": "なし", "service_supply_1": "なし", "service_supply_2": "なし", "service_supply_3": "なし", "nightdutyhaichi": "あり", "daily_life_price": "共用娯楽費・レクリエーション費は実費となります。ご家族様の宿泊費用は１泊につき３０００円。", "nintisyoshinritaio": "なし", "special_meal_price": "当施設で、ご用意する食事以外に入居者が希望される食事については、実費にて提供いたします。", "founding_day": "2007/12/01※半角で記入してください（例：2013/04/01）", "private_kinou": "あり", "kouku": "あり", "kangotaisei_2": "あり", "kangotaisei_1": "あり", "unit_privateroom": "", "latitude": "33.563723900000000", "nintisyosenmon_1": "なし", "nintisyosenmon_2": "なし", "syogaisyashien": "なし", "keikoiji": "なし", "fax": "092-892-3344", "carestaffkaizen_3": "なし", "carestaffkaizen_2": "なし", "carestaffkaizen_1": "あり", "small_kyoten": "なし", "company_type": "社会福祉法人（社協以外）", "company": "社会福祉法人　千草会", "unit_semi_privateroom": "", "residence_price": "１日あたり２２７０円です。ただし、国が定める負担限度額段階（第１段階から第３段階）に該当される方は、１日あたり第１段階の方　８２０円、第２段階の方　８２０円、第３段階の方　１６４０円となります。", "doctor_haiti": "なし", "service_type": "\n地域密着型介護老人福祉施設入所者生活介護", "caregiving": "あり", "traffic": "福岡市営地下鉄「姪浜駅」から西鉄バスにて「福重2丁目」「壱岐東小学校」下車後、徒歩５分\r\n福岡市営地下鉄七隈線「橋本駅」下車、徒歩１５分", "medical_meal": "あり", "existingroom": "", "hairdressing_price": "訪問理美容の方が月２回施設に来園されます。カット、パーマ、カラーリング、顔そり等は実費にて訪問理美容業者へと支払っていただきます。ちなみにカット代は１２００円となっております。", "name": "特別養護老人ホーム　マイネスハウス福重", "multibedroom": "", "taisyojisoudan": "なし", "meal_price": "１日あたり１７００円（食費は、食材料費及び調理費用相当の金額です）ただし、国が定める負担限度額段階（第１段階から第３段階）に該当される方は、１日あたり第１段階の方　３００円、第２段階の方　３９０円、第３段階の方　６５０円となります。", "taisyomaesoudan": "なし", "seishinkairyo": "なし", "longitude": "130.320588499999980", "koukutaisei": "なし", "address_1": "福岡市西区福重2丁目34－5", "userchargecut": "なし", "office_no": "4091200057", "address_2": "", "special_room_price": "特別室は設けておりません。"},
{"jyakunenseinyusyo": "なし", "hp_address": "http://www.ikiiki8ta.jp/", "tel": "092-651-5518", "taisyogoshido": "なし", "taisyomaerenkei": "なし", "eiyomanage": "なし", "municipality": "福岡市東区", "manager_name": "山本　明美", "semi_unitcare": "なし", "nitijyokeizoku": "なし", "name_furi": "とくべつようごろうじんほーむいきいきはこざき", "zaitakuhukki": "なし", "postcode": "〒812-0053", "keikoikou": "なし", "zaitakunyusyo": "なし", "service_supply_1": "あり", "service_supply_2": "なし", "service_supply_3": "なし", "nightdutyhaichi": "あり", "daily_life_price": "持ち込みテレビ使用料（電気代として）３０円／日\r\n持ち込み冷蔵庫使用料（電気代として）３０円／日\r\nその他電気製品使用料（電気代として）　３円／日\r\nおやつ代　１００円／日\r\nサークル活動材料費　実費\r\n理美容費　実費", "nintisyoshinritaio": "なし", "special_meal_price": "なし", "founding_day": "2011/05/01※半角で記入してください（例：2013/04/01）", "private_kinou": "あり", "kouku": "なし", "kangotaisei_2": "あり", "kangotaisei_1": "あり", "unit_privateroom": "", "latitude": "33.625628900000000", "nintisyosenmon_1": "なし", "nintisyosenmon_2": "なし", "syogaisyashien": "なし", "keikoiji": "なし", "fax": "092-651-5537", "carestaffkaizen_3": "なし", "carestaffkaizen_2": "なし", "carestaffkaizen_1": "あり", "small_kyoten": "なし", "company_type": "社会福祉法人（社協以外）", "company": "ちどり福祉会", "unit_semi_privateroom": "", "residence_price": "ユニット型個室　１，９７０円／日\r\n国が定める基準費用額", "doctor_haiti": "なし", "service_type": "\n地域密着型介護老人福祉施設入所者生活介護", "caregiving": "なし", "traffic": "西鉄バス九大北門前下車　徒歩1分\r\n市営地下鉄箱崎九大前駅下車　徒歩5分\r\nJR箱崎駅下車　徒歩20分", "medical_meal": "あり", "existingroom": "", "hairdressing_price": "カット１，６００円、パーマ５，７００円　業者の提示価格", "name": "特別養護老人ホームいきいき箱崎", "multibedroom": "", "taisyojisoudan": "なし", "meal_price": "１，３８０円／日\r\n国が定める基準費用額", "taisyomaesoudan": "なし", "seishinkairyo": "なし", "longitude": "130.421485100000040", "koukutaisei": "あり", "address_1": "福岡県福岡市東区箱崎6丁目18番7号", "userchargecut": "あり", "office_no": "4090800139", "address_2": "", "special_room_price": "なし"},
{"jyakunenseinyusyo": "なし", "hp_address": "http://www.seiwakai-muta-hp.or.jp/welfare/", "tel": "092-874-7171", "taisyogoshido": "なし", "taisyomaerenkei": "なし", "eiyomanage": "なし", "municipality": "福岡市早良区", "manager_name": "宇佐　照子", "semi_unitcare": "なし", "nitijyokeizoku": "なし", "name_furi": "とくべつようごろうじんほーむ　まきのき", "zaitakuhukki": "なし", "postcode": "〒814-0163", "keikoikou": "なし", "zaitakunyusyo": "なし", "service_supply_1": "なし", "service_supply_2": "なし", "service_supply_3": "なし", "nightdutyhaichi": "あり", "daily_life_price": "日常生活にかかる費用や教養娯楽にかかる費用が実費で必要になることがあります。", "nintisyoshinritaio": "なし", "special_meal_price": "入居者が選定する特別な食事の費用については、実費となります。", "founding_day": "2012/6/1※半角で記入してください（例：2013/04/01）", "private_kinou": "あり", "kouku": "なし", "kangotaisei_2": "なし", "kangotaisei_1": "あり", "unit_privateroom": "", "latitude": "33.555527100000000", "nintisyosenmon_1": "なし", "nintisyosenmon_2": "なし", "syogaisyashien": "なし", "keikoiji": "なし", "fax": "092-864-1011", "carestaffkaizen_3": "なし", "carestaffkaizen_2": "なし", "carestaffkaizen_1": "あり", "small_kyoten": "なし", "company_type": "社会福祉法人（社協以外）", "company": "誠和会", "unit_semi_privateroom": "", "residence_price": "・居住費（１日当たり）　　1,900円\r\n　※ただし、利用者負担第１・２段階の方は820円、３段階の方は1,310円になります。", "doctor_haiti": "なし", "service_type": "\n地域密着型介護老人福祉施設入所者生活介護", "caregiving": "なし", "traffic": "・西鉄バス…3・17・200番系統、干隈バス停下車、徒歩3分\n\r\n・地下鉄……野芥駅下車、徒歩15分", "medical_meal": "あり", "existingroom": "", "hairdressing_price": "カット　1,500円、丸刈り　1,000円、カラー　3,000円、パーマ　5,000円\r\nカット＋顔そり　2,000円、カット＋カラー　4,500円、カット＋顔そり＋カラー　5,000円", "name": "特別養護老人ホーム　まきの木", "multibedroom": "", "taisyojisoudan": "なし", "meal_price": "・食事代（１日当たり）　　1,350円\r\n　※ただし、利用者負担第１段階の方は300円、２段階の方は390円、３段階の方は650円になります。\r\n・おやつ代　　200円", "taisyomaesoudan": "なし", "seishinkairyo": "なし", "longitude": "130.348942500000020", "koukutaisei": "なし", "address_1": "福岡市早良区干隈4丁目10番12号", "userchargecut": "あり", "office_no": "4091400160", "address_2": "", "special_room_price": "特になし。"},
{"jyakunenseinyusyo": "なし", "hp_address": "http://www.imayamakai.or.jp/", "tel": "092-807-3366", "taisyogoshido": "なし", "taisyomaerenkei": "なし", "eiyomanage": "なし", "municipality": "福岡市西区", "manager_name": "朝野　愛子", "semi_unitcare": "なし", "nitijyokeizoku": "あり", "name_furi": "とくべつようごろうじんほーむみのり", "zaitakuhukki": "なし", "postcode": "〒819-0383", "keikoikou": "なし", "zaitakunyusyo": "なし", "service_supply_1": "なし", "service_supply_2": "なし", "service_supply_3": "なし", "nightdutyhaichi": "あり", "daily_life_price": "なし", "nintisyoshinritaio": "なし", "special_meal_price": "実費", "founding_day": "2008/08/01※半角で記入してください（例：2013/04/01）", "private_kinou": "なし", "kouku": "なし", "kangotaisei_2": "なし", "kangotaisei_1": "なし", "unit_privateroom": "", "latitude": "33.588366100000000", "nintisyosenmon_1": "なし", "nintisyosenmon_2": "なし", "syogaisyashien": "なし", "keikoiji": "なし", "fax": "092-807-3365", "carestaffkaizen_3": "なし", "carestaffkaizen_2": "なし", "carestaffkaizen_1": "あり", "small_kyoten": "なし", "company_type": "社会福祉法人（社協以外）", "company": "今山会", "unit_semi_privateroom": "", "residence_price": "負担軽減あり。\r\n1日につき、第4段階 2600円  第3段階 1310円  第2段階 820円 第1段階 820円", "doctor_haiti": "なし", "service_type": "\n地域密着型介護老人福祉施設入所者生活介護", "caregiving": "あり", "traffic": "JR筑肥線　九大学研都市駅　徒歩15分　九大学研都市前バス停九大工学部行（元岡）　工芸会ワークセンター前より徒歩5分", "medical_meal": "なし", "existingroom": "", "hairdressing_price": "実費", "name": "特別養護老人ホーム 美の里", "multibedroom": "", "taisyojisoudan": "なし", "meal_price": "1日 合計 1380円 （朝 380円 昼 500円 夕500円）\r\n負担減額あり。 1日につき第４段階 1380円、第3段階 650円 第２段階 390円 第1段階 300円", "taisyomaesoudan": "なし", "seishinkairyo": "あり", "longitude": "130.255853700000000", "koukutaisei": "あり", "address_1": "福岡県福岡市西区大字田尻２５３５", "userchargecut": "なし", "office_no": "4091200107", "address_2": "", "special_room_price": "なし"},
{"jyakunenseinyusyo": "なし", "hp_address": "http://www.shoseien.jp/", "tel": "092-885-2945", "taisyogoshido": "なし", "taisyomaerenkei": "なし", "eiyomanage": "あり", "municipality": "福岡市西区", "manager_name": "土斐﨑公一", "semi_unitcare": "なし", "nitijyokeizoku": "あり", "name_furi": "とくべつようごろうじんほーむしょうせいえん", "zaitakuhukki": "なし", "postcode": "〒819-0162", "keikoikou": "なし", "zaitakunyusyo": "なし", "service_supply_1": "なし", "service_supply_2": "なし", "service_supply_3": "なし", "nightdutyhaichi": "あり", "daily_life_price": "無し", "nintisyoshinritaio": "なし", "special_meal_price": "無し", "founding_day": "2006/04/01※半角で記入してください（例：2013/04/01）", "private_kinou": "なし", "kouku": "なし", "kangotaisei_2": "あり", "kangotaisei_1": "あり", "unit_privateroom": "", "latitude": "33.576869200000000", "nintisyosenmon_1": "なし", "nintisyosenmon_2": "なし", "syogaisyashien": "なし", "keikoiji": "なし", "fax": "092-885-2948", "carestaffkaizen_3": "なし", "carestaffkaizen_2": "なし", "carestaffkaizen_1": "あり", "small_kyoten": "なし", "company_type": "社会福祉法人（社協以外）", "company": "社会福祉法人筑前伊都の会", "unit_semi_privateroom": "", "residence_price": "（1日あたり）\r\n所得段階　第1段階　820円　　第2段階　820円　　第3段階　　1310円　第4段階　1970円", "doctor_haiti": "なし", "service_type": "\n地域密着型介護老人福祉施設入所者生活介護", "caregiving": "なし", "traffic": "JR筑肥線　下山門駅から徒歩約20分\r\nJR筑肥線　今宿駅から徒歩約25分\r\n今宿姪浜線乗合タクシー・マイクロバス　大谷停留所から徒歩約10分", "medical_meal": "なし", "existingroom": "", "hairdressing_price": "カット　１，７００円　　パーマ　５，４００円　　顔そり　　１，２００円", "name": "特別養護老人ホーム松生園", "multibedroom": "", "taisyojisoudan": "なし", "meal_price": "（1日あたり）\r\n所得段階　第1段階　300円　　第2段階　390円　　第3段階　　650円　　第4段階　　1380円", "taisyomaesoudan": "なし", "seishinkairyo": "なし", "longitude": "130.291176899999980", "koukutaisei": "あり", "address_1": "福岡市西区今宿青木1093-22", "userchargecut": "あり", "office_no": "4091200180", "address_2": "", "special_room_price": "無し"},
{"jyakunenseinyusyo": "なし", "hp_address": "http://www.tatara-fukushikai.com/", "tel": "092－410－4146", "taisyogoshido": "なし", "taisyomaerenkei": "なし", "eiyomanage": "なし", "municipality": "福岡市東区", "manager_name": "仲西　恵美", "semi_unitcare": "なし", "nitijyokeizoku": "あり", "name_furi": "とくべつようごろうじんほーむ　つくしのさと", "zaitakuhukki": "なし", "postcode": "〒813-0024", "keikoikou": "なし", "zaitakunyusyo": "なし", "service_supply_1": "なし", "service_supply_2": "なし", "service_supply_3": "なし", "nightdutyhaichi": "あり", "daily_life_price": "（電気代）テレビ１月300円、ラジオ月額150円、冷蔵庫月額600円", "nintisyoshinritaio": "なし", "special_meal_price": "なし", "founding_day": "2012/4/1※半角で記入してください（例：2013/04/01）", "private_kinou": "なし", "kouku": "あり", "kangotaisei_2": "あり", "kangotaisei_1": "あり", "unit_privateroom": "", "latitude": "33.635823200000000", "nintisyosenmon_1": "なし", "nintisyosenmon_2": "なし", "syogaisyashien": "なし", "keikoiji": "なし", "fax": "092－410－4147", "carestaffkaizen_3": "なし", "carestaffkaizen_2": "なし", "carestaffkaizen_1": "あり", "small_kyoten": "なし", "company_type": "社会福祉法人（社協以外）", "company": "社会福祉法人　多々良福祉会", "unit_semi_privateroom": "", "residence_price": "１日1,870円", "doctor_haiti": "なし", "service_type": "\n地域密着型介護老人福祉施設入所者生活介護", "caregiving": "なし", "traffic": "・西鉄バス　―　　天神より名子行（77番）に乗車し名子道バス停で降りて、徒歩10分\n\r\n・ＪＲ電車　－　博多駅より鹿児島本線下りに乗車、ＪＲ香椎駅で香椎線宇美方面に乗り換え、ＪＲ土井駅で降りて徒歩20分", "medical_meal": "あり", "existingroom": "", "hairdressing_price": "1,200円(税別）", "name": "特別養護老人ホーム　つくしの里", "multibedroom": "", "taisyojisoudan": "なし", "meal_price": "１日1,380円　朝400円　昼490円　夕490円", "taisyomaesoudan": "なし", "seishinkairyo": "あり", "longitude": "130.475928100000030", "koukutaisei": "あり", "address_1": "福岡県福岡市東区名子1丁目16番10号", "userchargecut": "あり", "office_no": "4090800246", "address_2": "つくしの里  1丁目ユニット、2丁目ユニット、３丁目ユニット、新町（ショートステイ）ユニット", "special_room_price": "なし"},
{"jyakunenseinyusyo": "あり", "hp_address": "", "tel": "092-526-2800", "taisyogoshido": "なし", "taisyomaerenkei": "あり", "eiyomanage": "あり", "municipality": "福岡市中央区", "manager_name": "久保山宣彦", "semi_unitcare": "なし", "nitijyokeizoku": "なし", "name_furi": "おざさ", "zaitakuhukki": "なし", "postcode": "〒810-0033", "keikoikou": "なし", "zaitakunyusyo": "なし", "service_supply_1": "なし", "service_supply_2": "あり", "service_supply_3": "なし", "nightdutyhaichi": "あり", "daily_life_price": "実費", "nintisyoshinritaio": "なし", "special_meal_price": "現在の所、実績無し。", "founding_day": "2007/11/01※半角で記入してください（例：2013/04/01）", "private_kinou": "なし", "kouku": "なし", "kangotaisei_2": "あり", "kangotaisei_1": "あり", "unit_privateroom": "", "latitude": "33.563154900000000", "nintisyosenmon_1": "なし", "nintisyosenmon_2": "なし", "syogaisyashien": "なし", "keikoiji": "なし", "fax": "092-526-2802", "carestaffkaizen_3": "なし", "carestaffkaizen_2": "なし", "carestaffkaizen_1": "あり", "small_kyoten": "なし", "company_type": "社会福祉法人（社協以外）", "company": "社会福祉法人ふたば会", "unit_semi_privateroom": "", "residence_price": "第4段階の方は1日2,820円徴収している。", "doctor_haiti": "なし", "service_type": "\n地域密着型介護老人福祉施設入所者生活介護", "caregiving": "なし", "traffic": "西鉄電車平尾駅より2ｋｍ（車で5分ぐらい）\r\n小笹バス停より徒歩2分", "medical_meal": "あり", "existingroom": "", "hairdressing_price": "実費", "name": "おざさ", "multibedroom": "", "taisyojisoudan": "あり", "meal_price": "朝380円、昼500円、夕500円の1日1,380円", "taisyomaesoudan": "なし", "seishinkairyo": "あり", "longitude": "130.389800100000000", "koukutaisei": "あり", "address_1": "福岡市中央区小笹1丁目14-27", "userchargecut": "あり", "office_no": "4091000036", "address_2": "", "special_room_price": "現在の所、実績無し。"},
{"jyakunenseinyusyo": "なし", "hp_address": "http://sungardens.jp", "tel": "092-892-2310", "taisyogoshido": "なし", "taisyomaerenkei": "なし", "eiyomanage": "あり", "municipality": "福岡市西区", "manager_name": "野口　眞知子", "semi_unitcare": "なし", "nitijyokeizoku": "なし", "name_furi": "ちいきみっちゃくがたとくべつようごろうじんほーむさんがーでん", "zaitakuhukki": "なし", "postcode": "〒819-0038", "keikoikou": "なし", "zaitakunyusyo": "なし", "service_supply_1": "なし", "service_supply_2": "あり", "service_supply_3": "なし", "nightdutyhaichi": "あり", "daily_life_price": "電気使用料（電化製品1品につき）450円／月", "nintisyoshinritaio": "なし", "special_meal_price": "なし", "founding_day": "2011/05/01※半角で記入してください（例：2013/04/01）", "private_kinou": "なし", "kouku": "なし", "kangotaisei_2": "あり", "kangotaisei_1": "あり", "unit_privateroom": "", "latitude": "33.544472200000000", "nintisyosenmon_1": "なし", "nintisyosenmon_2": "なし", "syogaisyashien": "なし", "keikoiji": "なし", "fax": "092-892-2311", "carestaffkaizen_3": "なし", "carestaffkaizen_2": "なし", "carestaffkaizen_1": "あり", "small_kyoten": "なし", "company_type": "社会福祉法人（社協以外）", "company": "社会福祉法人　飯盛会", "unit_semi_privateroom": "", "residence_price": "負担軽減あり。1日につき、第4段階 1670円 第3段階 1310円 第2段階 820円 第1段階 820円", "doctor_haiti": "なし", "service_type": "\n地域密着型介護老人福祉施設入所者生活介護", "caregiving": "なし", "traffic": "地下鉄姪浜駅（南口）→西鉄バス(1)壱岐ヶ丘中学校・(1)金武営業所→壱岐ヶ丘中学校バス停→徒歩→サンガーデン\r\n地下鉄橋本駅→西鉄バス(1)壱岐ヶ丘中学校・(1)金武営業所→壱岐ヶ丘中学校バス停→徒歩→サンガーデン", "medical_meal": "なし", "existingroom": "", "hairdressing_price": "訪問理美容が月1回ございます。\r\n訪問理美容へ実費でのお支払となります。", "name": "地域密着型特別養護老人ホームサンガーデン", "multibedroom": "", "taisyojisoudan": "なし", "meal_price": "1日1380円 \r\n負担減額あり。 1日につき第４段階 1380円、第3段階 650円 第２段階 390円 第1段階 300円", "taisyomaesoudan": "なし", "seishinkairyo": "あり", "longitude": "130.309209499999950", "koukutaisei": "なし", "address_1": "福岡県福岡市西区羽根戸５２１", "userchargecut": "なし", "office_no": "4091200131", "address_2": "", "special_room_price": "なし"},
{"jyakunenseinyusyo": "なし", "hp_address": "", "tel": "092-592-5765", "taisyogoshido": "あり", "taisyomaerenkei": "あり", "eiyomanage": "あり", "municipality": "福岡市博多区", "manager_name": "宮脇　克明", "semi_unitcare": "なし", "nitijyokeizoku": "なし", "name_furi": "とくべつようごろうじんほーむ　りんごのいえ", "zaitakuhukki": "なし", "postcode": "〒812-0881", "keikoikou": "なし", "zaitakunyusyo": "なし", "service_supply_1": "なし", "service_supply_2": "なし", "service_supply_3": "なし", "nightdutyhaichi": "あり", "daily_life_price": "個人のものに関しては実費負担", "nintisyoshinritaio": "なし", "special_meal_price": "実費負担", "founding_day": "2011/02/01※半角で記入してください（例：2013/04/01）", "private_kinou": "なし", "kouku": "なし", "kangotaisei_2": "なし", "kangotaisei_1": "なし", "unit_privateroom": "", "latitude": "33.550699400000000", "nintisyosenmon_1": "なし", "nintisyosenmon_2": "なし", "syogaisyashien": "なし", "keikoiji": "なし", "fax": "092-592-5870", "carestaffkaizen_3": "なし", "carestaffkaizen_2": "なし", "carestaffkaizen_1": "あり", "small_kyoten": "なし", "company_type": "社会福祉法人（社協以外）", "company": "社会福祉法人そよかぜの会", "unit_semi_privateroom": "", "residence_price": "1日につき　1,500円", "doctor_haiti": "なし", "service_type": "\n地域密着型介護老人福祉施設入所者生活介護", "caregiving": "あり", "traffic": "西鉄雑餉隈駅から徒歩9分　　　　　　　　　　　　　　　　　　　　　　　　　　　　　　　　　　　　　　　　　　　　　　　　西鉄バス麦野バス停から徒歩3分", "medical_meal": "なし", "existingroom": "", "hairdressing_price": "訪問理美容：月2回訪問　カット　2,000円　オプション顔そり、シャンプー　プラス500円", "name": "特別養護老人ホーム　りんごの家", "multibedroom": "", "taisyojisoudan": "あり", "meal_price": "１日につき1,380円（朝：380円　昼：450円　夜：550円）", "taisyomaesoudan": "あり", "seishinkairyo": "なし", "longitude": "130.466705899999960", "koukutaisei": "あり", "address_1": "福岡県福岡市博多区井相田3-8-1", "userchargecut": "あり", "office_no": "4090900061", "address_2": "", "special_room_price": "実費負担"},
{"jyakunenseinyusyo": "なし", "hp_address": "", "tel": "092-663-8500", "taisyogoshido": "なし", "taisyomaerenkei": "なし", "eiyomanage": "なし", "municipality": "福岡市東区", "manager_name": "田中　瑞年", "semi_unitcare": "なし", "nitijyokeizoku": "あり", "name_furi": "ちいきみっちゃくがたかいごろうじんふくししせつてりは", "zaitakuhukki": "なし", "postcode": "〒813-0017", "keikoikou": "なし", "zaitakunyusyo": "なし", "service_supply_1": "なし", "service_supply_2": "なし", "service_supply_3": "なし", "nightdutyhaichi": "あり", "daily_life_price": "実費", "nintisyoshinritaio": "なし", "special_meal_price": "実費", "founding_day": "2013/04/01※半角で記入してください（例：2013/04/01）", "private_kinou": "あり", "kouku": "なし", "kangotaisei_2": "あり", "kangotaisei_1": "あり", "unit_privateroom": "", "latitude": "33.660577500000000", "nintisyosenmon_1": "なし", "nintisyosenmon_2": "なし", "syogaisyashien": "なし", "keikoiji": "なし", "fax": "092-663-8501", "carestaffkaizen_3": "なし", "carestaffkaizen_2": "なし", "carestaffkaizen_1": "あり", "small_kyoten": "なし", "company_type": "社会福祉法人（社協以外）", "company": "社会福祉法人　怡土福祉会", "unit_semi_privateroom": "", "residence_price": "1，970円（1日あたり）　建設費用、光熱水費、修繕、維持費用を1人/1日あたりの費用に換算", "doctor_haiti": "なし", "service_type": "\n地域密着型介護老人福祉施設入所者生活介護", "caregiving": "なし", "traffic": "JR千早駅、西鉄千早駅下車、千早駅前バス停よりシャトルバス利用。香椎照葉3丁目下車徒歩2分", "medical_meal": "あり", "existingroom": "", "hairdressing_price": "1，500（カット）その他", "name": "地域密着型介護老人福祉施設照葉", "multibedroom": "", "taisyojisoudan": "なし", "meal_price": "1，380円（1日あたり）　給食業務委託料と予定食材費を1人/1日あたりの費用に換算", "taisyomaesoudan": "なし", "seishinkairyo": "なし", "longitude": "130.421591600000060", "koukutaisei": "あり", "address_1": "福岡市東区香椎照葉3-4-3", "userchargecut": "あり", "office_no": "4090800261", "address_2": "", "special_room_price": "なし"},
{"jyakunenseinyusyo": "なし", "hp_address": "ｈｔｔｐ：/ｗｗｗ.aishinnooka.com", "tel": "092-503-9000", "taisyogoshido": "なし", "taisyomaerenkei": "なし", "eiyomanage": "なし", "municipality": "福岡市博多区", "manager_name": "丸山　貴裕", "semi_unitcare": "なし", "nitijyokeizoku": "なし", "name_furi": "つきぐまあいしんのおか", "zaitakuhukki": "なし", "postcode": "〒812-0858", "keikoikou": "なし", "zaitakunyusyo": "なし", "service_supply_1": "なし", "service_supply_2": "なし", "service_supply_3": "なし", "nightdutyhaichi": "なし", "daily_life_price": "なし", "nintisyoshinritaio": "なし", "special_meal_price": "なし", "founding_day": "2013/03/25※半角で記入してください（例：2013/04/01）", "private_kinou": "なし", "kouku": "なし", "kangotaisei_2": "なし", "kangotaisei_1": "あり", "unit_privateroom": "", "latitude": "33.571488600000000", "nintisyosenmon_1": "なし", "nintisyosenmon_2": "なし", "syogaisyashien": "なし", "keikoiji": "なし", "fax": "092-503-8988", "carestaffkaizen_3": "なし", "carestaffkaizen_2": "なし", "carestaffkaizen_1": "あり", "small_kyoten": "なし", "company_type": "社会福祉法人（社協以外）", "company": "福岡愛心の丘", "unit_semi_privateroom": "", "residence_price": "３７６円/１日（多床室）", "doctor_haiti": "なし", "service_type": "\n地域密着型介護老人福祉施設入所者生活介護", "caregiving": "あり", "traffic": "地下鉄（空港線）福岡空港駅下車　西鉄バス（43番線）上月隈バス停下車　徒歩約5分", "medical_meal": "あり", "existingroom": "", "hairdressing_price": "なし", "name": "月隈愛心の丘", "multibedroom": "", "taisyojisoudan": "なし", "meal_price": "１，３８０円/１日", "taisyomaesoudan": "なし", "seishinkairyo": "なし", "longitude": "130.466819699999970", "koukutaisei": "あり", "address_1": "福岡市博多区月隈6丁目16番11号", "userchargecut": "あり", "office_no": "4090900145", "address_2": "", "special_room_price": "なし"}]